enumhardlinks/__init__.py
enumhardlinks/enumhardlinks.py
enumhardlinks-0.0.1.dist-info/LICENSE
enumhardlinks-0.0.1.dist-info/METADATA
enumhardlinks-0.0.1.dist-info/WHEEL
enumhardlinks-0.0.1.dist-info/top_level.txt
enumhardlinks-0.0.1.dist-info/RECORD
